colorsort/__init__.py
colorsort/colorsort.py
colorsort-0.0.1.dist-info/LICENSE
colorsort-0.0.1.dist-info/METADATA
colorsort-0.0.1.dist-info/WHEEL
colorsort-0.0.1.dist-info/top_level.txt
colorsort-0.0.1.dist-info/RECORD
