Metadata-Version: 2.1
Name: colorsort
Version: 0.0.1
Summary: Perceptually sorted colors
Home-page: https://github.com/rowland-208/colorsort
Author: James Rowland
Author-email: rowland.208@gmail.com
License: UNKNOWN
Project-URL: Bug Tracker, https://github.com/rowland-208/colorsort/issues
Platform: UNKNOWN
Classifier: License :: OSI Approved :: MIT License
Classifier: Operating System :: OS Independent
Classifier: Programming Language :: Python
Classifier: Programming Language :: Python :: 3
Classifier: Programming Language :: Python :: 3.6
Classifier: Programming Language :: Python :: 3.7
Classifier: Programming Language :: Python :: 3.8
Classifier: Programming Language :: Python :: 3.9
Requires-Python: >=3.6
License-File: LICENSE
Requires-Dist: opencv-python (>=4.5.3)
Requires-Dist: colormath (>=3.0)
Requires-Dist: numpy (>=1.19.5)
Requires-Dist: ortools (>=9.0)
Requires-Dist: scipy (>=1.5.4)
